sherlock_mcp/__init__.py
sherlock_mcp/server.py
sherlock_mcp-0.1.5.dist-info/METADATA
sherlock_mcp-0.1.5.dist-info/WHEEL
sherlock_mcp-0.1.5.dist-info/entry_points.txt
sherlock_mcp-0.1.5.dist-info/RECORD
