Metadata-Version: 2.4
Name: sherlock-mcp
Version: 0.1.5
Summary: Shelock Domains MCP server to buy & manage domains
Author-email: Pol Alvarez <pol@fewsats.com>, Jordi Montes <jordi@fewsats.com>
Requires-Python: >=3.10
Requires-Dist: mcp>=1.4.1
Requires-Dist: sherlock-domains>=0.1.5
